dbbasic_email/__init__.py
dbbasic_email/cli.py
dbbasic_email-1.0.0.dist-info/licenses/LICENSE
dbbasic_email-1.0.0.dist-info/METADATA
dbbasic_email-1.0.0.dist-info/WHEEL
dbbasic_email-1.0.0.dist-info/top_level.txt
dbbasic_email-1.0.0.dist-info/RECORD
