Metadata-Version: 2.4
Name: dbbasic-email
Version: 1.0.0
Summary: Simple email queue with Unix mail support
Home-page: https://github.com/askrobots/dbbasic-email
Author: DBBasic Project
Author-email: dan@quellhorst.com
Project-URL: Bug Tracker, https://github.com/askrobots/dbbasic-email/issues
Project-URL: Documentation, https://github.com/askrobots/dbbasic-email#readme
Project-URL: Source Code, https://github.com/askrobots/dbbasic-email
Project-URL: Specification, http://dbbasic.com/email-spec
Keywords: email,smtp,mail,queue,unix mail,mbox
Classifier: Development Status :: 4 - Beta
Classifier: Intended Audience :: Developers
Classifier: Topic :: Software Development :: Libraries :: Python Modules
Classifier: Topic :: Communications :: Email
Classifier: License :: OSI Approved :: MIT License
Classifier: Programming Language :: Python :: 3
Classifier: Programming Language :: Python :: 3.6
Classifier: Programming Language :: Python :: 3.7
Classifier: Programming Language :: Python :: 3.8
Classifier: Programming Language :: Python :: 3.9
Classifier: Programming Language :: Python :: 3.10
Classifier: Programming Language :: Python :: 3.11
Classifier: Programming Language :: Python :: 3.12
Classifier: Operating System :: OS Independent
Requires-Python: >=3.6
License-File: LICENSE
Provides-Extra: queue
Requires-Dist: dbbasic-queue>=1.0.0; extra == "queue"
Provides-Extra: dev
Requires-Dist: pytest>=7.0.0; extra == "dev"
Requires-Dist: pytest-cov>=4.0.0; extra == "dev"
Dynamic: author
Dynamic: author-email
Dynamic: classifier
Dynamic: description
Dynamic: description-content-type
Dynamic: home-page
Dynamic: keywords
Dynamic: license-file
Dynamic: project-url
Dynamic: provides-extra
Dynamic: requires-python
Dynamic: summary
